tqenergymanager300/__init__.py
tqenergymanager300/tqenergymanager300.py
tqenergymanager300-0.0.2.dist-info/LICENSE
tqenergymanager300-0.0.2.dist-info/METADATA
tqenergymanager300-0.0.2.dist-info/WHEEL
tqenergymanager300-0.0.2.dist-info/top_level.txt
tqenergymanager300-0.0.2.dist-info/RECORD
