Metadata-Version: 2.1
Name: tqenergymanager300
Version: 0.0.2
Summary: Client for TQ-Automation Energy Manager 300 JSON API
Home-page: https://github.com/stieler-it/tqenergymanager300py
Author: stieler .IT
Author-email: michael@stieler.it
License: UNKNOWN
Project-URL: Bug Tracker, https://github.com/stieler-it/tqenergymanager300py/issues
Platform: UNKNOWN
Classifier: Programming Language :: Python :: 3
Classifier: License :: OSI Approved :: MIT License
Classifier: Operating System :: OS Independent
Requires-Python: >=3.6
